Automa_dio(Moore)/omega.sv
module omega (output z,input [1:2]st);

  assign z= st[1] & st[2];

endmodule

Automa_dio(Moore)/sigma.sv
module sigma (output [1:2]new_s,input [1:2]st,input [1:2]x);

  assign new_s[1]= ( !st[1] & st[2] & x[1] & !x[2] ) | ( st[1] & !st[2] & x[1] & x[2] );
  assign new_s[2]= ( !x[1] & x[2] ) | ( st[1] & !st[2] & x[1] & x[2] );

endmodule

Automa_dio(Moore)/registro.sv
module register (output reg [1:2]outreg, input [1:2]inreg, input en, input clk);

  initial begin
    outreg=2'b00;
  end

  always @ ( posedge clk ) begin
      if (en)
        outreg <= inreg;
  end

endmodule

Automa_dio(Moore)/machine.sv
module machine (output z,input [1:2]x,input clk);

  wire [1:2]sigma_regi;
  wire [1:2]regi_omega;

  register reg01 (regi_omega,sigma_regi,1'b1,clk);
  sigma sg (sigma_regi,regi_omega,x);
  omega om (z,regi_omega);

endmodule

Automa_dio(Moore)/test.sv
module test ();

  wire z;
  reg clk;
  reg [1:2]x;
  machine m1 (z,x,clk);

  parameter a= 2'b00;
  parameter d= 2'b01;
  parameter i= 2'b10;
  parameter o= 2'b11;

  initial begin
    clk=0;
  end

  always begin
    #3 clk=1;
    #1 clk=0;
  end

  initial begin
    $dumpfile ("wave.vcd");
    $dumpvars;
    x=d;
    #5 x=i;
    #4 x=o;
    #4 x=d;
    #20
    $finish;
  end

endmodule

Automa_dio(Moore)/wave.vcd
$date
	Mon Oct 21 12:58:50 2019
$end
$version
	Icarus Verilog
$end
$timescale
	1s
$end
$scope module test $end
$var wire 1 ! z $end
$var reg 1 " clk $end
$var reg 2 # x [1:2] $end
$scope module m1 $end
$var wire 1 " clk $end
$var wire 2 $ x [1:2] $end
$var wire 1 ! z $end
$var wire 2 % sigma_regi [1:2] $end
$var wire 2 & regi_omega [1:2] $end
$scope module om $end
$var wire 1 ! z $end
$var wire 2 ' st [1:2] $end
$upscope $end
$scope module reg01 $end
$var wire 1 " clk $end
$var wire 1 ( en $end
$var wire 2 ) inreg [1:2] $end
$var reg 2 * outreg [1:2] $end
$upscope $end
$scope module sg $end
$var wire 2 + st [1:2] $end
$var wire 2 , x [1:2] $end
$var wire 2 - new_s [1:2] $end
$upscope $end
$upscope $end
$upscope $end
$enddefinitions $end
#0
$dumpvars
b1 -
b1 ,
b0 +
b0 *
b1 )
1(
b0 '
b0 &
b1 %
b1 $
b1 #
0"
0!
$end
#3
b1 &
b1 '
b1 *
b1 +
1"
#4
0"
#5
b10 %
b10 )
b10 -
b10 #
b10 $
b10 ,
#7
b0 %
b0 )
b0 -
b10 &
b10 '
b10 *
b10 +
1"
#8
0"
#9
b11 %
b11 )
b11 -
b11 #
b11 $
b11 ,
#11
b0 %
b0 )
b0 -
1!
b11 &
b11 '
b11 *
b11 +
1"
#12
0"
#13
b1 %
b1 )
b1 -
b1 #
b1 $
b1 ,
#15
0!
b1 &
b1 '
b1 *
b1 +
1"
