ContatoreMod2(moore)/register.sv
module register (output reg new_state, input inState, input clk, input enable);

  initial begin
    new_state = 0;
  end

  always @ ( posedge clk ) begin

    if (enable)
      begin
        new_state <= inState;
      end

  end

endmodule

ContatoreMod2(moore)/sigma.sv
module sigma (output new_state, input state, input x);

  assign new_state= (!state & x) | (state & !x);

endmodule

ContatoreMod2(moore)/omega.sv
module omega (output z, input state);

  assign z= state;

endmodule

ContatoreMod2(moore)/automa.sv
module automa (output z, input x, input clk);

  wire sigma_regis;
  wire regis_omega;

  omega myOm(z,regis_omega);
  sigma mySig(sigma_regis,regis_omega,x);
  register regi(regis_omega,sigma_regis,clk,1'b1);

endmodule

ContatoreMod2(moore)/test.sv
module test();

  reg clk;
  reg x;
  wire z;
  automa fsm(z,x,clk);

  initial begin
    clk=0;
  end

  always
    begin
      #3 clk=1;
      #1 clk=0;
    end

  initial begin
    $dumpfile("wave.vcd");
    $dumpvars;
    #1 x=0;
    #4 x=1;
    #4 x=0;
    #4 x=1;
    #4 x=1;
    #4 x=0;
    #20
    $finish;
  end

endmodule

ContatoreMod2(moore)/wave.vcd
$date
	Fri Jan 10 11:39:10 2020
$end
$version
	Icarus Verilog
$end
$timescale
	1s
$end
$scope module test $end
$var wire 1 ! z $end
$var reg 1 " clk $end
$var reg 1 # x $end
$scope module fsm $end
$var wire 1 " clk $end
$var wire 1 # x $end
$var wire 1 ! z $end
$var wire 1 $ sigma_regis $end
$var wire 1 % regis_omega $end
$scope module myOm $end
$var wire 1 ! z $end
$var wire 1 % state $end
$upscope $end
$scope module mySig $end
$var wire 1 $ new_state $end
$var wire 1 # x $end
$var wire 1 % state $end
$upscope $end
$scope module regi $end
$var wire 1 " clk $end
$var wire 1 & enable $end
$var wire 1 $ inState $end
$var reg 1 % new_state $end
$upscope $end
$upscope $end
$upscope $end
$enddefinitions $end
#0
$dumpvars
1&
0%
x$
x#
0"
0!
$end
#1
0$
0#
#3
1"
#4
0"
#5
1$
1#
#7
0$
1!
1%
1"
#8
0"
#9
1$
0#
#11
1"
#12
0"
#13
0$
1#
#15
1$
0!
0%
1"
#16
0"
#19
0$
1!
1%
1"
#20
0"
#21
1$
0#
