FarmX4_1In-1Out/per2.sv
module per2 (output [N-1:0]z, input [N-1:0]in);

  parameter N=8; // per gestire numeri a 8 bit
  assign #2 z= in*2;

endmodule

FarmX4/per4.sv
module per4 (output [7:0]out,input [7:0]in,input clk); // per4 da 4dt

  wire [7:0]bridge;
  reg [7:0]in_data;
  per2 p1(bridge,in);
  per2 p2(out,bridge);

  always @ ( posedge clk ) begin
    in_data=in;
  end

endmodule

FarmX4_1In-1Out/per4farm.sv
module per4farm (output [7:0]res1,input [7:0]num1,input clk);

  reg [7:0]in_data1;

  per4 w1 (res1,in_data1,clk);
  per4 w2 (res1,in_data1,clk);

  always @ ( posedge clk ) begin
    in_data1 = num1;
  end

endmodule

FarmX4_1In-1Out/test.sv
module test();

  parameter N=8;

  reg clk;
  reg [N-1:0]num1;
  wire [N-1:0]res1;
  integer i;
  per4farm m1(res1,num1,clk);

  initial begin
    clk=0;
  end

  always begin
    #1 clk=1;
    #1 clk=0;
  end

  initial begin

    $dumpfile("wave.vcd");
    $dumpvars;
    #1
    for (i=0;i<9;i=i+1) begin
      #2
      num1 = i;
    end
    #30
    $finish;
  end

endmodule

FarmX4_1In-1Out/wave.vcd
$date
	Wed Oct 23 21:28:23 2019
$end
$version
	Icarus Verilog
$end
$timescale
	1s
$end
$scope module test $end
$var wire 8 ! res1 [7:0] $end
$var reg 1 " clk $end
$var reg 8 # num1 [7:0] $end
$var integer 32 $ i [31:0] $end
$scope module m1 $end
$var wire 1 " clk $end
$var wire 8 % num1 [7:0] $end
$var wire 8 & res1 [7:0] $end
$var reg 8 ' in_data1 [7:0] $end
$scope module w1 $end
$var wire 1 " clk $end
$var wire 8 ( in [7:0] $end
$var wire 8 ) out [7:0] $end
$var wire 8 * bridge [7:0] $end
$var reg 8 + in_data [7:0] $end
$scope module p1 $end
$var wire 8 , in [7:0] $end
$var wire 8 - z [7:0] $end
$upscope $end
$scope module p2 $end
$var wire 8 . in [7:0] $end
$var wire 8 / z [7:0] $end
$upscope $end
$upscope $end
$scope module w2 $end
$var wire 1 " clk $end
$var wire 8 0 in [7:0] $end
$var wire 8 1 out [7:0] $end
$var wire 8 2 bridge [7:0] $end
$var reg 8 3 in_data [7:0] $end
$scope module p1 $end
$var wire 8 4 in [7:0] $end
$var wire 8 5 z [7:0] $end
$upscope $end
$scope module p2 $end
$var wire 8 6 in [7:0] $end
$var wire 8 7 z [7:0] $end
$upscope $end
$upscope $end
$upscope $end
$upscope $end
$enddefinitions $end
#0
$dumpvars
bx 7
bx 6
bx 5
bx 4
bx 3
bx 2
bx 1
bx 0
bx /
bx .
bx -
bx ,
bx +
bx *
bx )
bx (
bx '
bx &
bx %
bx $
bx #
0"
bx !
$end
#1
b0 $
1"
#2
0"
#3
b0 '
b0 (
b0 ,
b0 0
b0 4
1"
b1 $
b0 #
b0 %
#4
0"
#5
b1 +
b1 3
b1 '
b1 (
b1 ,
b1 0
b1 4
1"
b0 *
b0 -
b0 .
b0 2
b0 5
b0 6
b10 $
b1 #
b1 %
#6
0"
#7
b10 '
b10 (
b10 ,
b10 0
b10 4
1"
b10 *
b10 -
b10 .
b10 2
b10 5
b10 6
b0 !
b0 &
b0 )
b0 /
b0 1
b0 7
b11 $
b10 #
b10 %
#8
0"
#9
b11 +
b11 3
b11 '
b11 (
b11 ,
b11 0
b11 4
1"
b100 *
b100 -
b100 .
b100 2
b100 5
b100 6
b100 !
b100 &
b100 )
b100 /
b100 1
b100 7
b100 $
b11 #
b11 %
#10
0"
#11
b100 '
b100 (
b100 ,
b100 0
b100 4
1"
b110 *
b110 -
b110 .
b110 2
b110 5
b110 6
b1000 !
b1000 &
b1000 )
b1000 /
b1000 1
b1000 7
b101 $
b100 #
b100 %
#12
0"
#13
b101 +
b101 3
b101 '
b101 (
b101 ,
b101 0
b101 4
1"
b1000 *
b1000 -
b1000 .
b1000 2
b1000 5
b1000 6
b1100 !
b1100 &
b1100 )
b1100 /
b1100 1
b1100 7
b110 $
b101 #
b101 %
#14
0"
#15
b110 '
b110 (
b110 ,
b110 0
b110 4
1"
b1010 *
b1010 -
b1010 .
b1010 2
b1010 5
b1010 6
b10000 !
b10000 &
b10000 )
b10000 /
b10000 1
b10000 7
b111 $
b110 #
b110 %
#16
0"
#17
b111 +
b111 3
b111 '
b111 (
b111 ,
b111 0
b111 4
1"
b1100 *
b1100 -
b1100 .
b1100 2
b1100 5
b1100 6
b10100 !
b10100 &
b10100 )
b10100 /
b10100 1
b10100 7
b1000 $
b111 #
b111 %
#18
0"
#19
b1000 '
b1000 (
b1000 ,
b1000 0
b1000 4
1"
b1110 *
b1110 -
b1110 .
b1110 2
b1110 5
b1110 6
b11000 !
b11000 &
b11000 )
b11000 /
b11000 1
b11000 7
b1001 $
b1000 #
b1000 %
#20
0"
#21
b1000 +
b1000 3
1"
b10000 *
b10000 -
b10000 .
b10000 2
b10000 5
b10000 6
b11100 !
b11100 &
b11100 )
b11100 /
b11100 1
b11100 7
#22
0"
#23
1"
b100000 !
b100000 &
b100000 )
b100000 /
b100000 1
b100000 7
