FarmX4_1In-1Out/per2.sv
module per2 (output [N-1:0]z, input [N-1:0]in);

  parameter N=8; // per gestire numeri a 8 bit
  assign #2 z= in*2;

endmodule

PipelineX4_2Stages/stage.sv
module stage (output [N-1:0]res, input [N-1:0]num, input clk);

  parameter N=8;
  reg [N-1:0]in_data;
  per2 p1 (res,in_data);

  always @ ( posedge clk ) begin
    in_data = num;
  end

endmodule

PipelineX4_2Stages/p4mod.sv
module p4mod (output [N-1:0]out,input [N-1:0]in,input clk);

  parameter N=8;

  wire [N-1:0]bridge;
  stage s1(bridge,in,clk);
  stage s2(out,bridge,clk);

endmodule

PipelineX4_2Stages/test.sv
module test();

  parameter N=8;

  reg clk;
  reg [N-1:0]numero;
  wire [N-1:0]result;
  integer i;
  p4mod m1(result,numero,clk);

  initial begin
    clk=0;
  end

  always begin
    #1 clk=1;
    #1 clk=0;
  end

  initial begin
    numero=0;
    $dumpfile("wave.vcd");
    $dumpvars;
    #1 numero=0;
    for (i=1;i<9;i=i+1)
      #2 numero = i;
    #20
    $finish;
  end

endmodule

PipelineX4_2Stages/wave.vcd
$date
	Wed Oct 23 10:29:56 2019
$end
$version
	Icarus Verilog
$end
$timescale
	1s
$end
$scope module test $end
$var wire 8 ! result [7:0] $end
$var reg 1 " clk $end
$var reg 8 # numero [7:0] $end
$var integer 32 $ i [31:0] $end
$scope module m1 $end
$var wire 1 " clk $end
$var wire 8 % in [7:0] $end
$var wire 8 & out [7:0] $end
$var wire 8 ' bridge [7:0] $end
$scope module s1 $end
$var wire 1 " clk $end
$var wire 8 ( num [7:0] $end
$var wire 8 ) res [7:0] $end
$var reg 8 * in_data [7:0] $end
$scope module p1 $end
$var wire 8 + in [7:0] $end
$var wire 8 , z [7:0] $end
$upscope $end
$upscope $end
$scope module s2 $end
$var wire 1 " clk $end
$var wire 8 - num [7:0] $end
$var wire 8 . res [7:0] $end
$var reg 8 / in_data [7:0] $end
$scope module p1 $end
$var wire 8 0 in [7:0] $end
$var wire 8 1 z [7:0] $end
$upscope $end
$upscope $end
$upscope $end
$upscope $end
$enddefinitions $end
#0
$dumpvars
bx 1
bx 0
bx /
bx .
bx -
bx ,
bx +
bx *
bx )
b0 (
bx '
bx &
b0 %
bx $
b0 #
0"
bx !
$end
#1
b0 *
b0 +
b1 $
1"
#2
0"
#3
b0 /
b0 0
b1 *
b1 +
1"
b0 '
b0 )
b0 ,
b0 -
b10 $
b1 #
b1 %
b1 (
#4
0"
#5
b10 *
b10 +
b10 /
b10 0
1"
b0 !
b0 &
b0 .
b0 1
b10 '
b10 )
b10 ,
b10 -
b11 $
b10 #
b10 %
b10 (
#6
0"
#7
b100 /
b100 0
b11 *
b11 +
1"
b100 '
b100 )
b100 ,
b100 -
b100 !
b100 &
b100 .
b100 1
b100 $
b11 #
b11 %
b11 (
#8
0"
#9
b100 *
b100 +
b110 /
b110 0
1"
b1000 !
b1000 &
b1000 .
b1000 1
b110 '
b110 )
b110 ,
b110 -
b101 $
b100 #
b100 %
b100 (
#10
0"
#11
b1000 /
b1000 0
b101 *
b101 +
1"
b1000 '
b1000 )
b1000 ,
b1000 -
b1100 !
b1100 &
b1100 .
b1100 1
b110 $
b101 #
b101 %
b101 (
#12
0"
#13
b110 *
b110 +
b1010 /
b1010 0
1"
b10000 !
b10000 &
b10000 .
b10000 1
b1010 '
b1010 )
b1010 ,
b1010 -
b111 $
b110 #
b110 %
b110 (
#14
0"
#15
b1100 /
b1100 0
b111 *
b111 +
1"
b1100 '
b1100 )
b1100 ,
b1100 -
b10100 !
b10100 &
b10100 .
b10100 1
b1000 $
b111 #
b111 %
b111 (
#16
0"
#17
b1000 *
b1000 +
b1110 /
b1110 0
1"
b11000 !
b11000 &
b11000 .
b11000 1
b1110 '
b1110 )
b1110 ,
b1110 -
b1001 $
b1000 #
b1000 %
b1000 (
#18
0"
#19
b10000 /
b10000 0
1"
b10000 '
b10000 )
b10000 ,
b10000 -
b11100 !
b11100 &
b11100 .
b11100 1
#20
0"
#21
1"
b100000 !
b100000 &
b100000 .
b100000 1
