Stack8/omega.sv
module omega (output [0:7]z, input [0:7]s);

  assign z= s;

endmodule

Stack8/sigma.sv
module sigma (output [0:7]new_s,input [0:7]s,input x);

  assign new_s[0]= s[1] & s[2] & s[3] & s[4] & s[5] & s[6] & s[7] & x;

  assign new_s[1]= (s[1] & s[2] & s[3] & s[4] & s[5] & s[6] & s[7] & x) |
                   (!s[0] & !s[1] & s[2] & s[3] & s[4] & s[5] & s[6] & s[7] & x) |
                   (s[0] & s[1] & s[2] & s[3] & s[4] & s[5] & s[6] & s[7] & !x);

  assign new_s[2]= (s[1] & s[2] & s[3] & s[4] & s[5] & s[6] & s[7] & x) |
                   (!s[0] & !s[1] & s[2] & s[3] & s[4] & s[5] & s[6] & s[7] & x) |
                   (s[0] & s[1] & s[2] & s[3] & s[4] & s[5] & s[6] & s[7] & !x) |
                   (!s[0] & !s[1] & !s[2] & s[3] & s[4] & s[5] & s[6] & s[7] & x) |
                   (!s[0] & s[1] & s[2] & s[3] & s[4] & s[5] & s[6] & s[7] & !x);

  assign new_s[3]= (s[1] & s[2] & s[3] & s[4] & s[5] & s[6] & s[7] & x) |
                   (!s[0] & !s[1] & s[2] & s[3] & s[4] & s[5] & s[6] & s[7] & x) |
                   (s[0] & s[1] & s[2] & s[3] & s[4] & s[5] & s[6] & s[7] & !x) |
                   (!s[0] & !s[1] & !s[2] & s[3] & s[4] & s[5] & s[6] & s[7] & x) |
                   (!s[0] & s[1] & s[2] & s[3] & s[4] & s[5] & s[6] & s[7] & !x) |
                   (!s[0] & !s[1] & !s[2] & !s[3] & s[4] & s[5] & s[6] & s[7] & x) |
                   (!s[0] & !s[1] & s[2] & s[3] & s[4] & s[5] & s[6] & s[7] & !x);

  assign new_s[4]= (s[1] & s[2] & s[3] & s[4] & s[5] & s[6] & s[7] & x) |
                   (!s[0] & !s[1] & s[2] & s[3] & s[4] & s[5] & s[6] & s[7] & x) |
                   (s[0] & s[1] & s[2] & s[3] & s[4] & s[5] & s[6] & s[7] & !x) |
                   (!s[0] & !s[1] & !s[2] & s[3] & s[4] & s[5] & s[6] & s[7] & x) |
                   (!s[0] & s[1] & s[2] & s[3] & s[4] & s[5] & s[6] & s[7] & !x) |
                   (!s[0] & !s[1] & !s[2] & !s[3] & s[4] & s[5] & s[6] & s[7] & x) |
                   (!s[0] & !s[1] & s[2] & s[3] & s[4] & s[5] & s[6] & s[7] & !x) |
                   (!s[0] & !s[1] & !s[2] & !s[3] & !s[4] & s[5] & s[6] & s[7] & x) |
                   (!s[0] & !s[1] & !s[2] & s[3] & s[4] & s[5] & s[6] & s[7] & !x);

  assign new_s[5]= (s[1] & s[2] & s[3] & s[4] & s[5] & s[6] & s[7] & x) |
                   (!s[0] & !s[1] & s[2] & s[3] & s[4] & s[5] & s[6] & s[7] & x) |
                   (s[0] & s[1] & s[2] & s[3] & s[4] & s[5] & s[6] & s[7] & !x) |
                   (!s[0] & !s[1] & !s[2] & s[3] & s[4] & s[5] & s[6] & s[7] & x) |
                   (!s[0] & s[1] & s[2] & s[3] & s[4] & s[5] & s[6] & s[7] & !x) |
                   (!s[0] & !s[1] & !s[2] & !s[3] & s[4] & s[5] & s[6] & s[7] & x) |
                   (!s[0] & !s[1] & s[2] & s[3] & s[4] & s[5] & s[6] & s[7] & !x) |
                   (!s[0] & !s[1] & !s[2] & !s[3] & !s[4] & s[5] & s[6] & s[7] & x) |
                   (!s[0] & !s[1] & !s[2] & s[3] & s[4] & s[5] & s[6] & s[7] & !x) |
                   (!s[0] & !s[1] & !s[2] & !s[3] & !s[4] & !s[5] & s[6] & s[7] & x) |
                   (!s[0] & !s[1] & !s[2] & !s[3] & s[4] & s[5] & s[6] & s[7] & !x);

  assign new_s[6]= (s[1] & s[2] & s[3] & s[4] & s[5] & s[6] & s[7] & x) |
                   (!s[0] & !s[1] & s[2] & s[3] & s[4] & s[5] & s[6] & s[7] & x) |
                   (s[0] & s[1] & s[2] & s[3] & s[4] & s[5] & s[6] & s[7] & !x) |
                   (!s[0] & !s[1] & !s[2] & s[3] & s[4] & s[5] & s[6] & s[7] & x) |
                   (!s[0] & s[1] & s[2] & s[3] & s[4] & s[5] & s[6] & s[7] & !x) |
                   (!s[0] & !s[1] & !s[2] & !s[3] & s[4] & s[5] & s[6] & s[7] & x) |
                   (!s[0] & !s[1] & s[2] & s[3] & s[4] & s[5] & s[6] & s[7] & !x) |
                   (!s[0] & !s[1] & !s[2] & !s[3] & !s[4] & s[5] & s[6] & s[7] & x) |
                   (!s[0] & !s[1] & !s[2] & s[3] & s[4] & s[5] & s[6] & s[7] & !x) |
                   (!s[0] & !s[1] & !s[2] & !s[3] & !s[4] & !s[5] & s[6] & s[7] & x) |
                   (!s[0] & !s[1] & !s[2] & !s[3] & s[4] & s[5] & s[6] & s[7] & !x) |
                   (!s[0] & !s[1] & !s[2] & !s[3] & !s[4] & !s[5] & !s[6] & s[7] & x) |
                   (!s[0] & !s[1] & !s[2] & !s[3] & !s[4] & s[5] & s[6] & s[7] & !x);

  assign new_s[7]= (s[1] & s[2] & s[3] & s[4] & s[5] & s[6] & s[7] & x) |
                   (!s[0] & !s[1] & s[2] & s[3] & s[4] & s[5] & s[6] & s[7] & x) |
                   (s[0] & s[1] & s[2] & s[3] & s[4] & s[5] & s[6] & s[7] & !x) |
                   (!s[0] & !s[1] & !s[2] & s[3] & s[4] & s[5] & s[6] & s[7] & x) |
                   (!s[0] & s[1] & s[2] & s[3] & s[4] & s[5] & s[6] & s[7] & !x) |
                   (!s[0] & !s[1] & !s[2] & !s[3] & s[4] & s[5] & s[6] & s[7] & x) |
                   (!s[0] & !s[1] & s[2] & s[3] & s[4] & s[5] & s[6] & s[7] & !x) |
                   (!s[0] & !s[1] & !s[2] & !s[3] & !s[4] & s[5] & s[6] & s[7] & x) |
                   (!s[0] & !s[1] & !s[2] & s[3] & s[4] & s[5] & s[6] & s[7] & !x) |
                   (!s[0] & !s[1] & !s[2] & !s[3] & !s[4] & !s[5] & s[6] & s[7] & x) |
                   (!s[0] & !s[1] & !s[2] & !s[3] & s[4] & s[5] & s[6] & s[7] & !x) |
                   (!s[0] & !s[1] & !s[2] & !s[3] & !s[4] & !s[5] & !s[6] & s[7] & x) |
                   (!s[0] & !s[1] & !s[2] & !s[3] & !s[4] & s[5] & s[6] & s[7] & !x) |
                   (!s[0] & !s[1] & !s[2] & !s[3] & !s[4] & !s[5] & !s[6] & !s[7] & x) |
                   (!s[0] & !s[1] & !s[2] & !s[3] & !s[4] & !s[5] & s[6] & s[7] & !x);

endmodule

Stack8/register.sv
module register (output reg [0:7]outreg,input [0:7]inreg,input enable,input clk);

  initial begin
    outreg[0]=0;
    outreg[1]=0;
    outreg[2]=0;
    outreg[3]=0;
    outreg[4]=0;
    outreg[5]=0;
    outreg[6]=0;
    outreg[7]=0;
  end

  always @ ( posedge clk ) begin
    if (enable)
      outreg <= inreg;

  end

endmodule

Stack8/stack8.sv
module stack8 (output [0:7]z,input x,input clk);

  wire [0:7]sg_rg;
  wire [0:7]rg_om;
  register r01 (rg_om,sg_rg,1'b1,clk);
  sigma sg (sg_rg,rg_om,x);
  omega om (z,rg_om);

endmodule

Stack8/test.sv
module test ();

  reg x;
  reg clk;
  wire [0:7]z;
  stack8 stk (z,x,clk);

  initial begin
    clk=0;
  end

  always  begin
    #4 clk=1;
    #2 clk=0;
  end

  initial begin
    $dumpfile("wave.vcd");
    $dumpvars;
    x=0;
    #3 x=1;
    #6 x=1;
    #6 x=1;
    #6 x=0;
    #6 x=0;
    #6 x=0;
    #6 x=1;
    #10
    $finish;
  end

endmodule // test

Stack8/wave.vcd
$date
	Wed Oct 30 20:00:57 2019
$end
$version
	Icarus Verilog
$end
$timescale
	1s
$end
$scope module test $end
$var wire 8 ! z [0:7] $end
$var reg 1 " clk $end
$var reg 1 # x $end
$scope module stk $end
$var wire 1 " clk $end
$var wire 1 # x $end
$var wire 8 $ z [0:7] $end
$var wire 8 % sg_rg [0:7] $end
$var wire 8 & rg_om [0:7] $end
$scope module om $end
$var wire 8 ' z [0:7] $end
$var wire 8 ( s [0:7] $end
$upscope $end
$scope module r01 $end
$var wire 1 " clk $end
$var wire 1 ) enable $end
$var wire 8 * inreg [0:7] $end
$var reg 8 + outreg [0:7] $end
$upscope $end
$scope module sg $end
$var wire 8 , s [0:7] $end
$var wire 1 # x $end
$var wire 8 - new_s [0:7] $end
$upscope $end
$upscope $end
$upscope $end
$enddefinitions $end
#0
$dumpvars
b0 -
b0 ,
b0 +
b0 *
1)
b0 (
b0 '
b0 &
b0 %
b0 $
0#
0"
b0 !
$end
#3
b1 %
b1 *
b1 -
1#
#4
b11 %
b11 *
b11 -
b1 !
b1 $
b1 '
b1 &
b1 (
b1 +
b1 ,
1"
#6
0"
#10
b111 %
b111 *
b111 -
b11 !
b11 $
b11 '
b11 &
b11 (
b11 +
b11 ,
1"
#12
0"
#16
b1111 %
b1111 *
b1111 -
b111 !
b111 $
b111 '
b111 &
b111 (
b111 +
b111 ,
1"
#18
0"
#21
b11 %
b11 *
b11 -
0#
#22
b1 %
b1 *
b1 -
b11 !
b11 $
b11 '
b11 &
b11 (
b11 +
b11 ,
1"
#24
0"
#28
b0 %
b0 *
b0 -
b1 !
b1 $
b1 '
b1 &
b1 (
b1 +
b1 ,
1"
#30
0"
#34
b0 !
b0 $
b0 '
b0 &
b0 (
b0 +
b0 ,
1"
#36
0"
#39
b1 %
b1 *
b1 -
1#
#40
b11 %
b11 *
b11 -
b1 !
b1 $
b1 '
b1 &
b1 (
b1 +
b1 ,
1"
#42
0"
#46
b111 %
b111 *
b111 -
b11 !
b11 $
b11 '
b11 &
b11 (
b11 +
b11 ,
1"
